Users/ruigao/.strategyease_sdk/config/logging-template.ini
Users/ruigao/.strategyease_sdk/config/scheduler-template.ini
examples/__init__.py
examples/basic_example.py
examples/joinquant/__init__.py
examples/joinquant/advanced_strategy.py
examples/joinquant/convertible_bonds_purchase.py
examples/joinquant/new_stocks_purchase.py
examples/joinquant/repo.py
examples/joinquant/simple_runner.py
examples/joinquant/simple_strategy.py
examples/joinquant/simple_sync_strategy.py
examples/joinquant/simply_strategy.py
examples/ricequant/__init__.py
examples/ricequant/advanced_strategy.py
examples/ricequant/convertible_bonds_purchase.py
examples/ricequant/new_stocks_purchase.py
examples/ricequant/repo.py
examples/ricequant/simple_strategy.py
shipane_sdk/__init__.py
shipane_sdk/ap.py
shipane_sdk/base_manager.py
shipane_sdk/base_quant_client.py
shipane_sdk/client.py
shipane_sdk/market_utils.py
shipane_sdk/models.py
shipane_sdk/scheduler.py
shipane_sdk/stock.py
shipane_sdk/support.py
shipane_sdk/transaction.py
shipane_sdk/guorn/__init__.py
shipane_sdk/guorn/client.py
shipane_sdk/jobs/__init__.py
shipane_sdk/jobs/basic_job.py
shipane_sdk/jobs/batch.py
shipane_sdk/jobs/new_stock_purchase.py
shipane_sdk/jobs/online_quant_following.py
shipane_sdk/jobs/online_quant_sync.py
shipane_sdk/jobs/repo.py
shipane_sdk/joinquant/__init__.py
shipane_sdk/joinquant/client.py
shipane_sdk/joinquant/executor.py
shipane_sdk/joinquant/manager.py
shipane_sdk/joinquant/runner.py
shipane_sdk/joinquant/transaction.py
shipane_sdk/ricequant/__init__.py
shipane_sdk/ricequant/client.py
shipane_sdk/ricequant/manager.py
shipane_sdk/ricequant/transaction.py
shipane_sdk/uqer/__init__.py
shipane_sdk/uqer/client.py
shipane_sdk/uqer/transaction.py
strategyease_sdk/__init__.py
strategyease_sdk/ap.py
strategyease_sdk/base_manager.py
strategyease_sdk/base_quant_client.py
strategyease_sdk/client.py
strategyease_sdk/market_utils.py
strategyease_sdk/models.py
strategyease_sdk/scheduler.py
strategyease_sdk/stock.py
strategyease_sdk-2.1.0.dist-info/LICENSE.txt
strategyease_sdk-2.1.0.dist-info/METADATA
strategyease_sdk-2.1.0.dist-info/WHEEL
strategyease_sdk-2.1.0.dist-info/entry_points.txt
strategyease_sdk-2.1.0.dist-info/top_level.txt
strategyease_sdk-2.1.0.dist-info/RECORD
