Metadata-Version: 2.1
Name: strategyease-sdk
Version: 2.1.0
Summary: 策略易（StrategyEase）Python SDK，策略自动化交易 API。
Home-page: https://github.com/sinall/StrategyEase-Python-SDK
Author: sinall
Author-email: gaoruinan@163.com
License: MIT
Keywords: StrategyEase SDK
Platform: UNKNOWN
Classifier: Development Status :: 3 - Alpha
Classifier: Intended Audience :: Developers
Classifier: Intended Audience :: Financial and Insurance Industry
Classifier: Topic :: Office/Business :: Financial :: Investment
Classifier: License :: OSI Approved :: MIT License
Classifier: Programming Language :: Python :: 2.7
Classifier: Programming Language :: Python :: 3
Classifier: Programming Language :: Python :: 3.3
Classifier: Programming Language :: Python :: 3.4
Classifier: Programming Language :: Python :: 3.5
Classifier: Programming Language :: Python :: 3.6
Classifier: Programming Language :: Python :: 3.7
Requires-Dist: requests
Requires-Dist: six
Requires-Dist: apscheduler
Requires-Dist: lxml
Requires-Dist: cssselect
Requires-Dist: bs4
Requires-Dist: html5lib
Requires-Dist: pandas
Requires-Dist: tushare
Requires-Dist: pyyaml
Provides-Extra: dev
Provides-Extra: test
